dismoji/__init__.py
dismoji/_version.py
dismoji/py.typed
dismoji/raw/LICENSE
dismoji/raw/build/.emojis.json.hash
dismoji/raw/build/.gitkeep
dismoji/raw/build/emojis.json
dismoji-0.3.1.dist-info/METADATA
dismoji-0.3.1.dist-info/WHEEL
dismoji-0.3.1.dist-info/licenses/LICENSE
dismoji-0.3.1.dist-info/RECORD
