Metadata-Version: 2.4
Name: dismoji
Version: 0.3.1
Summary: A Python library for converting Discord emoji names to their Unicode equivalents.
Project-URL: Homepage, https://github.com/Paillat-dev/dismoji
Project-URL: source_archive, https://github.com/Paillat-dev/dismoji/archive/83f4c1aae6acf7d8abf041a246bfc8d20ebd7e85.zip
Author-email: Paillat-dev <me@paillat.dev>
License-Expression: MIT
License-File: LICENSE
Keywords: bot,discord,emoji,emojis
Classifier: Development Status :: 3 - Alpha
Classifier: Intended Audience :: Developers
Classifier: License :: OSI Approved :: MIT License
Classifier: Operating System :: OS Independent
Classifier: Programming Language :: Python :: 3 :: Only
Classifier: Programming Language :: Python :: 3.10
Classifier: Programming Language :: Python :: 3.11
Classifier: Programming Language :: Python :: 3.12
Classifier: Programming Language :: Python :: 3.13
Classifier: Programming Language :: Python :: 3.14
Classifier: Typing :: Typed
Requires-Python: <3.15,>=3.10
